{
  "run_tag": "integration_n3k_noak",
  "seeds": [
    17,
    11,
    23,
    1,
    2,
    3,
    5,
    7,
    13,
    19
  ],
  "missing": [],
  "rows": [
    {
      "seed": 17,
      "n": 225,
      "A_R10": 0.32,
      "B_R10": 0.3244444444444444,
      "C_R10": 0.3422222222222222,
      "A_top1": 0.1288888888888889,
      "B_top1": 0.10222222222222223,
      "C_top1": 0.06222222222222222,
      "A_capt5": 0.28,
      "B_capt5": 0.26222222222222225,
      "C_capt5": 0.31555555555555553,
      "A_ms2": 0.4222222222222222,
      "B_ms2": 0.0,
      "C_ms2": 0.0,
      "A_ms3": 0.9955555555555555,
      "B_ms3": 0.7733333333333333,
      "C_ms3": 0.0,
      "A_ms4": 0.7022222222222222,
      "B_ms4": 1.0,
      "C_ms4": 0.0,
      "C_cands": 104,
      "C_cons": 328,
      "C_deaths": 7201,
      "C_drift": 0.0
    },
    {
      "seed": 11,
      "n": 210,
      "A_R10": 0.3619,
      "B_R10": 0.3762,
      "C_R10": 0.3714,
      "A_top1": 0.1095,
      "B_top1": 0.0857,
      "C_top1": 0.019,
      "A_capt5": 0.2381,
      "B_capt5": 0.3429,
      "C_capt5": 0.2333,
      "A_ms2": 0.014,
      "B_ms2": 0.0,
      "C_ms2": 0.0,
      "A_ms3": 0.486,
      "B_ms3": 1.0,
      "C_ms3": 0.0,
      "A_ms4": 1.0,
      "B_ms4": 1.0,
      "C_ms4": 0.0,
      "C_cands": 85,
      "C_cons": 571,
      "C_deaths": 7216,
      "C_drift": 0.0
    },
    {
      "seed": 23,
      "n": 217,
      "A_R10": 0.3624,
      "B_R10": 0.3581,
      "C_R10": 0.3493,
      "A_top1": 0.0786,
      "B_top1": 0.0917,
      "C_top1": 0.0524,
      "A_capt5": 0.2402,
      "B_capt5": 0.2489,
      "C_capt5": 0.1441,
      "A_ms2": 0.0,
      "B_ms2": 0.0,
      "C_ms2": 0.0,
      "A_ms3": 0.751,
      "B_ms3": 1.0,
      "C_ms3": 0.0,
      "A_ms4": 0.913,
      "B_ms4": 0.9,
      "C_ms4": 0.0,
      "C_cands": 83,
      "C_cons": 273,
      "C_deaths": 7219,
      "C_drift": 0.0
    },
    {
      "seed": 1,
      "n": 227,
      "A_R10": 0.3392,
      "B_R10": 0.3524,
      "C_R10": 0.3656,
      "A_top1": 0.0793,
      "B_top1": 0.0661,
      "C_top1": 0.1233,
      "A_capt5": 0.2115,
      "B_capt5": 0.2247,
      "C_capt5": 0.2643,
      "A_ms2": 0.004,
      "B_ms2": 0.546,
      "C_ms2": 0.0,
      "A_ms3": 0.555,
      "B_ms3": 0.604,
      "C_ms3": 0.0,
      "A_ms4": 1.0,
      "B_ms4": 1.0,
      "C_ms4": 0.0,
      "C_cands": 81,
      "C_cons": 52,
      "C_deaths": 7218,
      "C_drift": 0.0
    },
    {
      "seed": 2,
      "n": 220,
      "A_R10": 0.2909,
      "B_R10": 0.3091,
      "C_R10": 0.2955,
      "A_top1": 0.1136,
      "B_top1": 0.0636,
      "C_top1": 0.0273,
      "A_capt5": 0.2273,
      "B_capt5": 0.2273,
      "C_capt5": 0.0773,
      "A_ms2": 0.041,
      "B_ms2": 0.318,
      "C_ms2": 0.0,
      "A_ms3": 0.927,
      "B_ms3": 0.414,
      "C_ms3": 0.0,
      "A_ms4": 0.6,
      "B_ms4": 0.791,
      "C_ms4": 0.0,
      "C_cands": 80,
      "C_cons": 246,
      "C_deaths": 7221,
      "C_drift": 0.0
    },
    {
      "seed": 3,
      "n": 218,
      "A_R10": 0.3716,
      "B_R10": 0.3716,
      "C_R10": 0.3624,
      "A_top1": 0.1147,
      "B_top1": 0.0872,
      "C_top1": 0.0505,
      "A_capt5": 0.2661,
      "B_capt5": 0.2752,
      "C_capt5": 0.0963,
      "A_ms2": 0.0,
      "B_ms2": 0.252,
      "C_ms2": 0.0,
      "A_ms3": 0.881,
      "B_ms3": 0.844,
      "C_ms3": 0.0,
      "A_ms4": 0.881,
      "B_ms4": 0.858,
      "C_ms4": 0.0,
      "C_cands": 83,
      "C_cons": 294,
      "C_deaths": 7221,
      "C_drift": 2.02e-05
    },
    {
      "seed": 5,
      "n": 214,
      "A_R10": 0.285,
      "B_R10": 0.2757,
      "C_R10": 0.2757,
      "A_top1": 0.1262,
      "B_top1": 0.0935,
      "C_top1": 0.1121,
      "A_capt5": 0.243,
      "B_capt5": 0.2336,
      "C_capt5": 0.215,
      "A_ms2": 0.467,
      "B_ms2": 0.481,
      "C_ms2": 0.0,
      "A_ms3": 0.799,
      "B_ms3": 0.907,
      "C_ms3": 0.0,
      "A_ms4": 0.949,
      "B_ms4": 0.986,
      "C_ms4": 0.0,
      "C_cands": 108,
      "C_cons": 122,
      "C_deaths": 7214,
      "C_drift": 0.0
    },
    {
      "seed": 7,
      "n": 232,
      "A_R10": 0.3448,
      "B_R10": 0.3664,
      "C_R10": 0.3707,
      "A_top1": 0.1422,
      "B_top1": 0.0647,
      "C_top1": 0.0172,
      "A_capt5": 0.2759,
      "B_capt5": 0.3491,
      "C_capt5": 0.181,
      "A_ms2": 0.0,
      "B_ms2": 0.017,
      "C_ms2": 0.0,
      "A_ms3": 0.996,
      "B_ms3": 0.556,
      "C_ms3": 0.0,
      "A_ms4": 0.875,
      "B_ms4": 0.978,
      "C_ms4": 0.0,
      "C_cands": 63,
      "C_cons": 481,
      "C_deaths": 7204,
      "C_drift": 0.0
    },
    {
      "seed": 13,
      "n": 215,
      "A_R10": 0.3116,
      "B_R10": 0.3349,
      "C_R10": 0.3302,
      "A_top1": 0.1023,
      "B_top1": 0.0977,
      "C_top1": 0.0884,
      "A_capt5": 0.2512,
      "B_capt5": 0.2837,
      "C_capt5": 0.1953,
      "A_ms2": 0.019,
      "B_ms2": 0.595,
      "C_ms2": 0.0,
      "A_ms3": 1.0,
      "B_ms3": 0.567,
      "C_ms3": 0.0,
      "A_ms4": 0.86,
      "B_ms4": 0.851,
      "C_ms4": 0.0,
      "C_cands": 78,
      "C_cons": 134,
      "C_deaths": 7207,
      "C_drift": 0.0
    },
    {
      "seed": 19,
      "n": 223,
      "A_R10": 0.3049,
      "B_R10": 0.2915,
      "C_R10": 0.3184,
      "A_top1": 0.0762,
      "B_top1": 0.0717,
      "C_top1": 0.0404,
      "A_capt5": 0.139,
      "B_capt5": 0.1435,
      "C_capt5": 0.13,
      "A_ms2": 0.018,
      "B_ms2": 0.081,
      "C_ms2": 0.0,
      "A_ms3": 0.529,
      "B_ms3": 0.538,
      "C_ms3": 0.0,
      "A_ms4": 0.897,
      "B_ms4": 0.964,
      "C_ms4": 0.0,
      "C_cands": 81,
      "C_cons": 251,
      "C_deaths": 7220,
      "C_drift": 0.0
    }
  ],
  "headline_d1_ms_w3_CA": {
    "label": "\u0394ms_w3 (CA)",
    "mean": -0.7919555555555555,
    "std": 0.20362406658798257,
    "ci_lo": -0.9376093178496266,
    "ci_hi": -0.6463017932614844,
    "pos": 0,
    "neg": 10,
    "zero": 0,
    "ci_excludes_zero": true,
    "per_seed": [
      -0.9955555555555555,
      -0.486,
      -0.751,
      -0.555,
      -0.927,
      -0.881,
      -0.799,
      -0.996,
      -1.0,
      -0.529
    ],
    "headline": true
  },
  "d1_w2_CA": {
    "label": "\u0394ms_w2 (CA)",
    "mean": -0.09852222222222222,
    "std": 0.18314302917611272,
    "ci_lo": -0.2295257508542743,
    "ci_hi": 0.032481306409829866,
    "pos": 0,
    "neg": 7,
    "zero": 3,
    "ci_excludes_zero": false,
    "per_seed": [
      -0.4222222222222222,
      -0.014,
      0.0,
      -0.004,
      -0.041,
      0.0,
      -0.467,
      0.0,
      -0.019,
      -0.018
    ],
    "headline": false
  },
  "d1_w4_CA": {
    "label": "\u0394ms_w4 (CA)",
    "mean": -0.8677222222222222,
    "std": 0.12643070126445644,
    "ci_lo": -0.9581590139886267,
    "ci_hi": -0.7772854304558177,
    "pos": 0,
    "neg": 10,
    "zero": 0,
    "ci_excludes_zero": true,
    "per_seed": [
      -0.7022222222222222,
      -1.0,
      -0.913,
      -1.0,
      -0.6,
      -0.881,
      -0.949,
      -0.875,
      -0.86,
      -0.897
    ],
    "headline": false
  },
  "d1_w3_CB": {
    "label": "\u0394ms_w3 (CB)",
    "mean": -0.7203333333333334,
    "std": 0.2109526890964821,
    "ci_lo": -0.8712293121231385,
    "ci_hi": -0.5694373545435283,
    "pos": 0,
    "neg": 10,
    "zero": 0,
    "ci_excludes_zero": true,
    "per_seed": [
      -0.7733333333333333,
      -1.0,
      -1.0,
      -0.604,
      -0.414,
      -0.844,
      -0.907,
      -0.556,
      -0.567,
      -0.538
    ],
    "headline": false
  },
  "R10_CA": {
    "label": "\u0394R@10 (CA)",
    "mean": 0.00891222222222222,
    "std": 0.015091130990349958,
    "ci_lo": -0.0018825725328828653,
    "ci_hi": 0.019707016977327307,
    "pos": 7,
    "neg": 3,
    "zero": 0,
    "ci_excludes_zero": false,
    "per_seed": [
      0.0222222222222222,
      0.009500000000000008,
      -0.0131,
      0.02639999999999998,
      0.004599999999999993,
      -0.009199999999999986,
      -0.009299999999999975,
      0.02589999999999998,
      0.018600000000000005,
      0.013500000000000012
    ],
    "headline": false
  },
  "R10_CB": {
    "label": "\u0394R@10 (CB)",
    "mean": 0.002107777777777786,
    "std": 0.013250291867272255,
    "ci_lo": -0.007370251486159123,
    "ci_hi": 0.011585807041714696,
    "pos": 4,
    "neg": 5,
    "zero": 1,
    "ci_excludes_zero": false,
    "per_seed": [
      0.01777777777777778,
      -0.004799999999999971,
      -0.008799999999999975,
      0.01319999999999999,
      -0.013600000000000001,
      -0.009199999999999986,
      0.0,
      0.0042999999999999705,
      -0.004699999999999982,
      0.026900000000000035
    ],
    "headline": false
  },
  "capt5_CA": {
    "label": "\u0394cap_t05 (CA)",
    "mean": -0.052014444444444446,
    "std": 0.07496897374708658,
    "ci_lo": -0.1056402916468942,
    "ci_hi": 0.0016114027580053092,
    "pos": 2,
    "neg": 8,
    "zero": 0,
    "ci_excludes_zero": false,
    "per_seed": [
      0.03555555555555551,
      -0.004799999999999999,
      -0.09609999999999999,
      0.052799999999999986,
      -0.15000000000000002,
      -0.1698,
      -0.027999999999999997,
      -0.09489999999999998,
      -0.05589999999999998,
      -0.009000000000000008
    ],
    "headline": false
  },
  "top1_CA": {
    "label": "\u0394top1 (CA)",
    "mean": -0.04786666666666667,
    "std": 0.04854888334528483,
    "ci_lo": -0.08259403280224722,
    "ci_hi": -0.013139300531086119,
    "pos": 1,
    "neg": 9,
    "zero": 0,
    "ci_excludes_zero": true,
    "per_seed": [
      -0.06666666666666667,
      -0.0905,
      -0.0262,
      0.04400000000000001,
      -0.0863,
      -0.0642,
      -0.014100000000000001,
      -0.125,
      -0.013899999999999996,
      -0.035800000000000005
    ],
    "headline": false
  },
  "pooled_R10": {
    "A": {
      "k": 725,
      "n": 2201,
      "p": 0.3293957292139936,
      "ci": [
        0.31007251321385837,
        0.3493134490248801
      ]
    },
    "C": {
      "k": 745,
      "n": 2201,
      "p": 0.3384825079509314,
      "ci": [
        0.31901014665588684,
        0.3585177084063543
      ]
    },
    "delta": 0.00908677873693775
  }
}