{
  "config": {
    "dim": 4096,
    "device": null,
    "max_vocab": 2048,
    "corpus_source": "wikitext",
    "wikitext_name": "wikitext-2-raw-v1",
    "seed": 17,
    "codebook_path": "reports/phase3c_reconstruction/phase3c_codebook_reconstruction.pt",
    "scale_landscape": "2:4096,3:2048,4:1024",
    "eval_window_size": 8,
    "mask_position": "center",
    "beta": 10.0,
    "decode_k": 10,
    "rank_k": 50,
    "atom_sample_pairs": 100000,
    "n_cues": 2000,
    "checkpoint_every": 500,
    "drift_magnitude": 0.3,
    "test_samples": 400,
    "replay_every": 50,
    "replay_batch_size": 10,
    "store_threshold": 0.05,
    "resolve_threshold": 0.7,
    "store_capacity": 500,
    "consolidation_m": 6,
    "consolidation_alpha": 0.25,
    "novelty_strength": 1.0,
    "retrieval_gain": 0.1,
    "death_window": 1000,
    "death_threshold": 0.005,
    "reencode_every": 100,
    "output_dir": "reports/phase4_drift_0p30"
  },
  "results": {
    "baseline": [
      {
        "top1": 0.12244897959183673,
        "topk": 0.30952380952380953,
        "cap_t_03": 0.30952380952380953,
        "cap_t_05": 0.2755102040816326,
        "recall_at_k": {
          "1": 0.12244897959183673,
          "5": 0.23809523809523808,
          "10": 0.30952380952380953,
          "20": 0.3741496598639456,
          "50": 0.3877551020408163
        },
        "per_scale": {
          "2": {
            "mean_top_score": 0.9543128611684657,
            "mean_entropy": 0.7296215084945263,
            "metastable_rate": 0.4421768707482993,
            "recall_at_k": {
              "1": 0.12244897959183673,
              "5": 0.24489795918367346,
              "10": 0.3333333333333333,
              "20": 0.3979591836734694,
              "50": 0.47278911564625853
            },
            "mean_settled_synergy_at_mask": -0.006281335044614211,
            "atom_pair_geometry": {
              "n_pairs": 100000,
              "mean": 0.4102353788114339,
              "std": 0.03225641030834313,
              "p95": 0.45158186852931975,
              "p99": 0.4692427709698676,
              "max": 0.6612575054168701
            }
          },
          "3": {
            "mean_top_score": 0.8876099028960377,
            "mean_entropy": 0.7856069853922136,
            "metastable_rate": 0.9931972789115646,
            "recall_at_k": {
              "1": 0.09863945578231292,
              "5": 0.22108843537414966,
              "10": 0.3129251700680272,
              "20": 0.38095238095238093,
              "50": 0.4421768707482993
            },
            "mean_settled_synergy_at_mask": 0.14807024743759586,
            "atom_pair_geometry": {
              "n_pairs": 100000,
              "mean": 0.4102353788114339,
              "std": 0.03225641030834313,
              "p95": 0.45158186852931975,
              "p99": 0.4692427709698676,
              "max": 0.6612575054168701
            }
          },
          "4": {
            "mean_top_score": 0.8327003861365675,
            "mean_entropy": 0.7450994307897529,
            "metastable_rate": 0.717687074829932,
            "recall_at_k": {
              "1": 0.07482993197278912,
              "5": 0.19387755102040816,
              "10": 0.22789115646258504,
              "20": 0.29931972789115646,
              "50": 0.36394557823129253
            },
            "mean_settled_synergy_at_mask": 0.10591754989621711,
            "atom_pair_geometry": {
              "n_pairs": 100000,
              "mean": 0.4102353788114339,
              "std": 0.03225641030834313,
              "p95": 0.45158186852931975,
              "p99": 0.4692427709698676,
              "max": 0.6612575054168701
            }
          }
        },
        "n": 294,
        "cues_seen": 0,
        "condition": "baseline"
      },
      {
        "top1": 0.12244897959183673,
        "topk": 0.3299319727891156,
        "cap_t_03": 0.3299319727891156,
        "cap_t_05": 0.25510204081632654,
        "recall_at_k": {
          "1": 0.12244897959183673,
          "5": 0.24489795918367346,
          "10": 0.3299319727891156,
          "20": 0.391156462585034,
          "50": 0.391156462585034
        },
        "per_scale": {
          "2": {
            "mean_top_score": 0.9270834446358843,
            "mean_entropy": 0.7549038565888697,
            "metastable_rate": 0.46258503401360546,
            "recall_at_k": {
              "1": 0.12244897959183673,
              "5": 0.24149659863945577,
              "10": 0.3231292517006803,
              "20": 0.391156462585034,
              "50": 0.46258503401360546
            },
            "mean_settled_synergy_at_mask": 0.04105206902121466,
            "atom_pair_geometry": {
              "n_pairs": 100000,
              "mean": 0.39342050713323057,
              "std": 0.031210628255370843,
              "p95": 0.433834134042263,
              "p99": 0.4520974686741828,
              "max": 0.6365463733673096
            }
          },
          "3": {
            "mean_top_score": 0.8888191140833355,
            "mean_entropy": 0.7845116997657179,
            "metastable_rate": 0.9931972789115646,
            "recall_at_k": {
              "1": 0.09863945578231292,
              "5": 0.22448979591836735,
              "10": 0.30612244897959184,
              "20": 0.3877551020408163,
              "50": 0.445578231292517
            },
            "mean_settled_synergy_at_mask": 0.15054988725642282,
            "atom_pair_geometry": {
              "n_pairs": 100000,
              "mean": 0.39342050713323057,
              "std": 0.031210628255370843,
              "p95": 0.433834134042263,
              "p99": 0.4520974686741828,
              "max": 0.6365463733673096
            }
          },
          "4": {
            "mean_top_score": 0.8328415481817155,
            "mean_entropy": 0.7452584200975846,
            "metastable_rate": 0.717687074829932,
            "recall_at_k": {
              "1": 0.07482993197278912,
              "5": 0.1870748299319728,
              "10": 0.22789115646258504,
              "20": 0.29591836734693877,
              "50": 0.3673469387755102
            },
            "mean_settled_synergy_at_mask": 0.10309474988381986,
            "atom_pair_geometry": {
              "n_pairs": 100000,
              "mean": 0.39342050713323057,
              "std": 0.031210628255370843,
              "p95": 0.433834134042263,
              "p99": 0.4520974686741828,
              "max": 0.6365463733673096
            }
          }
        },
        "n": 294,
        "cues_seen": 500,
        "condition": "baseline"
      },
      {
        "top1": 0.09183673469387756,
        "topk": 0.2925170068027211,
        "cap_t_03": 0.282312925170068,
        "cap_t_05": 0.24829931972789115,
        "recall_at_k": {
          "1": 0.09183673469387756,
          "5": 0.22448979591836735,
          "10": 0.2925170068027211,
          "20": 0.3877551020408163,
          "50": 0.391156462585034
        },
        "per_scale": {
          "2": {
            "mean_top_score": 0.9993843168628459,
            "mean_entropy": 0.6920348900516017,
            "metastable_rate": 0.0,
            "recall_at_k": {
              "1": 0.04081632653061224,
              "5": 0.24829931972789115,
              "10": 0.3333333333333333,
              "20": 0.3979591836734694,
              "50": 0.46598639455782315
            },
            "mean_settled_synergy_at_mask": 1.169609572725738e-05,
            "atom_pair_geometry": {
              "n_pairs": 100000,
              "mean": 0.37563056520581245,
              "std": 0.030013411970681136,
              "p95": 0.4147272258996963,
              "p99": 0.43224036693573,
              "max": 0.6057379245758057
            }
          },
          "3": {
            "mean_top_score": 0.8895806943883702,
            "mean_entropy": 0.7845162353953536,
            "metastable_rate": 0.9931972789115646,
            "recall_at_k": {
              "1": 0.07482993197278912,
              "5": 0.21768707482993196,
              "10": 0.30612244897959184,
              "20": 0.35714285714285715,
              "50": 0.4421768707482993
            },
            "mean_settled_synergy_at_mask": 0.1431421092525283,
            "atom_pair_geometry": {
              "n_pairs": 100000,
              "mean": 0.37563056520581245,
              "std": 0.030013411970681136,
              "p95": 0.4147272258996963,
              "p99": 0.43224036693573,
              "max": 0.6057379245758057
            }
          },
          "4": {
            "mean_top_score": 0.8353367188349873,
            "mean_entropy": 0.7385677847327018,
            "metastable_rate": 0.7074829931972789,
            "recall_at_k": {
              "1": 0.07482993197278912,
              "5": 0.1870748299319728,
              "10": 0.22108843537414966,
              "20": 0.2857142857142857,
              "50": 0.35714285714285715
            },
            "mean_settled_synergy_at_mask": 0.10290733569255732,
            "atom_pair_geometry": {
              "n_pairs": 100000,
              "mean": 0.37563056520581245,
              "std": 0.030013411970681136,
              "p95": 0.4147272258996963,
              "p99": 0.43224036693573,
              "max": 0.6057379245758057
            }
          }
        },
        "n": 294,
        "cues_seen": 1000,
        "condition": "baseline"
      },
      {
        "top1": 0.09183673469387756,
        "topk": 0.2925170068027211,
        "cap_t_03": 0.2891156462585034,
        "cap_t_05": 0.22789115646258504,
        "recall_at_k": {
          "1": 0.09183673469387756,
          "5": 0.22448979591836735,
          "10": 0.2925170068027211,
          "20": 0.36394557823129253,
          "50": 0.37755102040816324
        },
        "per_scale": {
          "2": {
            "mean_top_score": 0.9995535883773752,
            "mean_entropy": 0.6860594512248526,
            "metastable_rate": 0.0,
            "recall_at_k": {
              "1": 0.04081632653061224,
              "5": 0.25170068027210885,
              "10": 0.3333333333333333,
              "20": 0.4013605442176871,
              "50": 0.46258503401360546
            },
            "mean_settled_synergy_at_mask": -0.0035399807744570786,
            "atom_pair_geometry": {
              "n_pairs": 100000,
              "mean": 0.35860527941077947,
              "std": 0.02882544429314986,
              "p95": 0.39637123048305506,
              "p99": 0.41300518721342083,
              "max": 0.580179750919342
            }
          },
          "3": {
            "mean_top_score": 0.8864489970158558,
            "mean_entropy": 0.7781095423665988,
            "metastable_rate": 0.9659863945578231,
            "recall_at_k": {
              "1": 0.07482993197278912,
              "5": 0.21768707482993196,
              "10": 0.29931972789115646,
              "20": 0.3877551020408163,
              "50": 0.45918367346938777
            },
            "mean_settled_synergy_at_mask": 0.1314196242059131,
            "atom_pair_geometry": {
              "n_pairs": 100000,
              "mean": 0.35860527941077947,
              "std": 0.02882544429314986,
              "p95": 0.39637123048305506,
              "p99": 0.41300518721342083,
              "max": 0.580179750919342
            }
          },
          "4": {
            "mean_top_score": 0.8382681632528499,
            "mean_entropy": 0.7275329605251754,
            "metastable_rate": 0.7108843537414966,
            "recall_at_k": {
              "1": 0.06462585034013606,
              "5": 0.17687074829931973,
              "10": 0.23129251700680273,
              "20": 0.2925170068027211,
              "50": 0.35714285714285715
            },
            "mean_settled_synergy_at_mask": 0.09869920486682507,
            "atom_pair_geometry": {
              "n_pairs": 100000,
              "mean": 0.35860527941077947,
              "std": 0.02882544429314986,
              "p95": 0.39637123048305506,
              "p99": 0.41300518721342083,
              "max": 0.580179750919342
            }
          }
        },
        "n": 294,
        "cues_seen": 1500,
        "condition": "baseline"
      },
      {
        "top1": 0.08843537414965986,
        "topk": 0.29591836734693877,
        "cap_t_03": 0.2789115646258503,
        "cap_t_05": 0.22108843537414966,
        "recall_at_k": {
          "1": 0.08843537414965986,
          "5": 0.21768707482993196,
          "10": 0.29591836734693877,
          "20": 0.36394557823129253,
          "50": 0.36394557823129253
        },
        "per_scale": {
          "2": {
            "mean_top_score": 0.9996865464716541,
            "mean_entropy": 0.6846649338598965,
            "metastable_rate": 0.0,
            "recall_at_k": {
              "1": 0.04081632653061224,
              "5": 0.25170068027210885,
              "10": 0.3333333333333333,
              "20": 0.40476190476190477,
              "50": 0.46258503401360546
            },
            "mean_settled_synergy_at_mask": -0.0075406254412524,
            "atom_pair_geometry": {
              "n_pairs": 100000,
              "mean": 0.34239038572259245,
              "std": 0.027705249697179017,
              "p95": 0.37879347205162045,
              "p99": 0.3948320081830024,
              "max": 0.5542756915092468
            }
          },
          "3": {
            "mean_top_score": 0.8868421845290125,
            "mean_entropy": 0.7717522392873051,
            "metastable_rate": 0.95578231292517,
            "recall_at_k": {
              "1": 0.07482993197278912,
              "5": 0.22448979591836735,
              "10": 0.2857142857142857,
              "20": 0.37755102040816324,
              "50": 0.4557823129251701
            },
            "mean_settled_synergy_at_mask": 0.11894739828694954,
            "atom_pair_geometry": {
              "n_pairs": 100000,
              "mean": 0.34239038572259245,
              "std": 0.027705249697179017,
              "p95": 0.37879347205162045,
              "p99": 0.3948320081830024,
              "max": 0.5542756915092468
            }
          },
          "4": {
            "mean_top_score": 0.8385623612371432,
            "mean_entropy": 0.7173684918556084,
            "metastable_rate": 0.6972789115646258,
            "recall_at_k": {
              "1": 0.04081632653061224,
              "5": 0.14625850340136054,
              "10": 0.2108843537414966,
              "20": 0.2789115646258503,
              "50": 0.35034013605442177
            },
            "mean_settled_synergy_at_mask": 0.09771460149362747,
            "atom_pair_geometry": {
              "n_pairs": 100000,
              "mean": 0.34239038572259245,
              "std": 0.027705249697179017,
              "p95": 0.37879347205162045,
              "p99": 0.3948320081830024,
              "max": 0.5542756915092468
            }
          }
        },
        "n": 294,
        "cues_seen": 2000,
        "condition": "baseline"
      }
    ],
    "phase4": [
      {
        "top1": 0.12244897959183673,
        "topk": 0.30952380952380953,
        "cap_t_03": 0.30952380952380953,
        "cap_t_05": 0.2755102040816326,
        "recall_at_k": {
          "1": 0.12244897959183673,
          "5": 0.23809523809523808,
          "10": 0.30952380952380953,
          "20": 0.3741496598639456,
          "50": 0.3877551020408163
        },
        "per_scale": {
          "2": {
            "mean_top_score": 0.9543128611684657,
            "mean_entropy": 0.7296215084945263,
            "metastable_rate": 0.4421768707482993,
            "recall_at_k": {
              "1": 0.12244897959183673,
              "5": 0.24489795918367346,
              "10": 0.3333333333333333,
              "20": 0.3979591836734694,
              "50": 0.47278911564625853
            },
            "mean_settled_synergy_at_mask": -0.006281335044614211,
            "atom_pair_geometry": {
              "n_pairs": 100000,
              "mean": 0.4102353788114339,
              "std": 0.03225641030834313,
              "p95": 0.45158186852931975,
              "p99": 0.4692427709698676,
              "max": 0.6612575054168701
            }
          },
          "3": {
            "mean_top_score": 0.8876099028960377,
            "mean_entropy": 0.7856069853922136,
            "metastable_rate": 0.9931972789115646,
            "recall_at_k": {
              "1": 0.09863945578231292,
              "5": 0.22108843537414966,
              "10": 0.3129251700680272,
              "20": 0.38095238095238093,
              "50": 0.4421768707482993
            },
            "mean_settled_synergy_at_mask": 0.14807024743759586,
            "atom_pair_geometry": {
              "n_pairs": 100000,
              "mean": 0.4102353788114339,
              "std": 0.03225641030834313,
              "p95": 0.45158186852931975,
              "p99": 0.4692427709698676,
              "max": 0.6612575054168701
            }
          },
          "4": {
            "mean_top_score": 0.8327003861365675,
            "mean_entropy": 0.7450994307897529,
            "metastable_rate": 0.717687074829932,
            "recall_at_k": {
              "1": 0.07482993197278912,
              "5": 0.19387755102040816,
              "10": 0.22789115646258504,
              "20": 0.29931972789115646,
              "50": 0.36394557823129253
            },
            "mean_settled_synergy_at_mask": 0.10591754989621711,
            "atom_pair_geometry": {
              "n_pairs": 100000,
              "mean": 0.4102353788114339,
              "std": 0.03225641030834313,
              "p95": 0.45158186852931975,
              "p99": 0.4692427709698676,
              "max": 0.6612575054168701
            }
          }
        },
        "n": 294,
        "cues_seen": 0,
        "condition": "phase4",
        "phase4_stats_w2": {
          "retrievals": 0,
          "candidates_total": 0,
          "store": {
            "size": 0,
            "capacity": 500,
            "evicted": 0,
            "mean_gate": 0.0,
            "max_gate": 0.0,
            "mean_age": 0.0,
            "mean_tag_count": 0.0,
            "max_tag_count": 0,
            "mean_suppression": 0.0
          },
          "consolidation": {
            "n_patterns": 4096,
            "mean_strength": 1.0,
            "max_strength": 1.0,
            "mean_u": [
              1.0,
              0.0,
              0.0,
              0.0,
              0.0,
              0.0
            ],
            "patterns_below_threshold": 0,
            "patterns_dead": 0,
            "step_count": 0
          },
          "memory_size": 4096
        },
        "phase4_stats_w3": {
          "retrievals": 0,
          "candidates_total": 0,
          "store": {
            "size": 0,
            "capacity": 500,
            "evicted": 0,
            "mean_gate": 0.0,
            "max_gate": 0.0,
            "mean_age": 0.0,
            "mean_tag_count": 0.0,
            "max_tag_count": 0,
            "mean_suppression": 0.0
          },
          "consolidation": {
            "n_patterns": 2048,
            "mean_strength": 1.0,
            "max_strength": 1.0,
            "mean_u": [
              1.0,
              0.0,
              0.0,
              0.0,
              0.0,
              0.0
            ],
            "patterns_below_threshold": 0,
            "patterns_dead": 0,
            "step_count": 0
          },
          "memory_size": 2048
        },
        "phase4_stats_w4": {
          "retrievals": 0,
          "candidates_total": 0,
          "store": {
            "size": 0,
            "capacity": 500,
            "evicted": 0,
            "mean_gate": 0.0,
            "max_gate": 0.0,
            "mean_age": 0.0,
            "mean_tag_count": 0.0,
            "max_tag_count": 0,
            "mean_suppression": 0.0
          },
          "consolidation": {
            "n_patterns": 1024,
            "mean_strength": 1.0,
            "max_strength": 1.0,
            "mean_u": [
              1.0,
              0.0,
              0.0,
              0.0,
              0.0,
              0.0
            ],
            "patterns_below_threshold": 0,
            "patterns_dead": 0,
            "step_count": 0
          },
          "memory_size": 1024
        }
      },
      {
        "top1": 0.12244897959183673,
        "topk": 0.3129251700680272,
        "cap_t_03": 0.3129251700680272,
        "cap_t_05": 0.24829931972789115,
        "recall_at_k": {
          "1": 0.12244897959183673,
          "5": 0.23129251700680273,
          "10": 0.3129251700680272,
          "20": 0.3741496598639456,
          "50": 0.3843537414965986
        },
        "per_scale": {
          "2": {
            "mean_top_score": 0.9996457412129357,
            "mean_entropy": 0.6989851425699636,
            "metastable_rate": 0.0,
            "recall_at_k": {
              "1": 0.12244897959183673,
              "5": 0.24829931972789115,
              "10": 0.3333333333333333,
              "20": 0.3945578231292517,
              "50": 0.46938775510204084
            },
            "mean_settled_synergy_at_mask": -0.001321196914444595,
            "atom_pair_geometry": {
              "n_pairs": 100000,
              "mean": 0.39342050713323057,
              "std": 0.031210628255370843,
              "p95": 0.433834134042263,
              "p99": 0.4520974686741828,
              "max": 0.6365463733673096
            }
          },
          "3": {
            "mean_top_score": 0.9999985796253698,
            "mean_entropy": 0.7308452528755681,
            "metastable_rate": 0.0,
            "recall_at_k": {
              "1": 0.09183673469387756,
              "5": 0.22448979591836735,
              "10": 0.30612244897959184,
              "20": 0.391156462585034,
              "50": 0.4421768707482993
            },
            "mean_settled_synergy_at_mask": 0.13198411399910392,
            "atom_pair_geometry": {
              "n_pairs": 100000,
              "mean": 0.39342050713323057,
              "std": 0.031210628255370843,
              "p95": 0.433834134042263,
              "p99": 0.4520974686741828,
              "max": 0.6365463733673096
            }
          },
          "4": {
            "mean_top_score": 0.9645628975767667,
            "mean_entropy": 0.6443790450793545,
            "metastable_rate": 0.24829931972789115,
            "recall_at_k": {
              "1": 0.05782312925170068,
              "5": 0.20068027210884354,
              "10": 0.25510204081632654,
              "20": 0.3231292517006803,
              "50": 0.4013605442176871
            },
            "mean_settled_synergy_at_mask": 0.06531244598021795,
            "atom_pair_geometry": {
              "n_pairs": 100000,
              "mean": 0.39342050713323057,
              "std": 0.031210628255370843,
              "p95": 0.433834134042263,
              "p99": 0.4520974686741828,
              "max": 0.6365463733673096
            }
          }
        },
        "n": 294,
        "cues_seen": 500,
        "condition": "phase4",
        "phase4_stats_w2": {
          "retrievals": 500,
          "candidates_total": 30,
          "store": {
            "size": 0,
            "capacity": 500,
            "evicted": 0,
            "mean_gate": 0.0,
            "max_gate": 0.0,
            "mean_age": 0.0,
            "mean_tag_count": 0.0,
            "max_tag_count": 0,
            "mean_suppression": 0.0
          },
          "consolidation": {
            "n_patterns": 4126,
            "mean_strength": 0.13326223194599152,
            "max_strength": 3.5944972038269043,
            "mean_u": [
              0.05819893628358841,
              0.08828923106193542,
              0.08422782272100449,
              0.059573013335466385,
              0.0323098823428154,
              0.012663357891142368
            ],
            "patterns_below_threshold": 0,
            "patterns_dead": 0,
            "step_count": 10
          },
          "memory_size": 4126
        },
        "phase4_stats_w3": {
          "retrievals": 500,
          "candidates_total": 34,
          "store": {
            "size": 0,
            "capacity": 500,
            "evicted": 0,
            "mean_gate": 0.0,
            "max_gate": 0.0,
            "mean_age": 0.0,
            "mean_tag_count": 0.0,
            "max_tag_count": 0,
            "mean_suppression": 0.0
          },
          "consolidation": {
            "n_patterns": 2082,
            "mean_strength": 0.1367853283882141,
            "max_strength": 13.049861907958984,
            "mean_u": [
              0.06035618111491203,
              0.09036001563072205,
              0.08529962599277496,
              0.06000695377588272,
              0.03243272006511688,
              0.01268182322382927
            ],
            "patterns_below_threshold": 0,
            "patterns_dead": 0,
            "step_count": 10
          },
          "memory_size": 2082
        },
        "phase4_stats_w4": {
          "retrievals": 500,
          "candidates_total": 40,
          "store": {
            "size": 0,
            "capacity": 500,
            "evicted": 0,
            "mean_gate": 0.0,
            "max_gate": 0.0,
            "mean_age": 0.0,
            "mean_tag_count": 0.0,
            "max_tag_count": 0,
            "mean_suppression": 0.0
          },
          "consolidation": {
            "n_patterns": 1064,
            "mean_strength": 0.1437855213880539,
            "max_strength": 13.18115234375,
            "mean_u": [
              0.06464007496833801,
              0.09449472278356552,
              0.08743293583393097,
              0.06083153560757637,
              0.03262927755713463,
              0.012690371833741665
            ],
            "patterns_below_threshold": 0,
            "patterns_dead": 0,
            "step_count": 10
          },
          "memory_size": 1064
        }
      },
      {
        "top1": 0.09523809523809523,
        "topk": 0.30272108843537415,
        "cap_t_03": 0.29931972789115646,
        "cap_t_05": 0.24829931972789115,
        "recall_at_k": {
          "1": 0.09523809523809523,
          "5": 0.23129251700680273,
          "10": 0.30272108843537415,
          "20": 0.38095238095238093,
          "50": 0.3843537414965986
        },
        "per_scale": {
          "2": {
            "mean_top_score": 0.9963548740967602,
            "mean_entropy": 0.7032413464419696,
            "metastable_rate": 0.02040816326530612,
            "recall_at_k": {
              "1": 0.04081632653061224,
              "5": 0.24829931972789115,
              "10": 0.3333333333333333,
              "20": 0.3979591836734694,
              "50": 0.46598639455782315
            },
            "mean_settled_synergy_at_mask": -0.0006782617352643133,
            "atom_pair_geometry": {
              "n_pairs": 100000,
              "mean": 0.37563056520581245,
              "std": 0.030013411970681136,
              "p95": 0.4147272258996963,
              "p99": 0.43224036693573,
              "max": 0.6057379245758057
            }
          },
          "3": {
            "mean_top_score": 0.9872882281030927,
            "mean_entropy": 0.7272260359355381,
            "metastable_rate": 0.0,
            "recall_at_k": {
              "1": 0.09183673469387756,
              "5": 0.21768707482993196,
              "10": 0.30612244897959184,
              "20": 0.35714285714285715,
              "50": 0.4421768707482993
            },
            "mean_settled_synergy_at_mask": 0.1274001970740675,
            "atom_pair_geometry": {
              "n_pairs": 100000,
              "mean": 0.37563056520581245,
              "std": 0.030013411970681136,
              "p95": 0.4147272258996963,
              "p99": 0.43224036693573,
              "max": 0.6057379245758057
            }
          },
          "4": {
            "mean_top_score": 0.9626035931564513,
            "mean_entropy": 0.6389921946184975,
            "metastable_rate": 0.2687074829931973,
            "recall_at_k": {
              "1": 0.05442176870748299,
              "5": 0.19387755102040816,
              "10": 0.24489795918367346,
              "20": 0.30612244897959184,
              "50": 0.3707482993197279
            },
            "mean_settled_synergy_at_mask": 0.062311445058760594,
            "atom_pair_geometry": {
              "n_pairs": 100000,
              "mean": 0.37563056520581245,
              "std": 0.030013411970681136,
              "p95": 0.4147272258996963,
              "p99": 0.43224036693573,
              "max": 0.6057379245758057
            }
          }
        },
        "n": 294,
        "cues_seen": 1000,
        "condition": "phase4",
        "phase4_stats_w2": {
          "retrievals": 1000,
          "candidates_total": 30,
          "store": {
            "size": 0,
            "capacity": 500,
            "evicted": 0,
            "mean_gate": 0.0,
            "max_gate": 0.0,
            "mean_age": 0.0,
            "mean_tag_count": 0.0,
            "max_tag_count": 0,
            "mean_suppression": 0.0
          },
          "consolidation": {
            "n_patterns": 4126,
            "mean_strength": 0.06496173143386841,
            "max_strength": 9.929597854614258,
            "mean_u": [
              0.024677149951457977,
              0.04111582413315773,
              0.047017619013786316,
              0.04334419220685959,
              0.032340239733457565,
              0.017055092379450798
            ],
            "patterns_below_threshold": 0,
            "patterns_dead": 0,
            "step_count": 20
          },
          "memory_size": 4126
        },
        "phase4_stats_w3": {
          "retrievals": 1000,
          "candidates_total": 34,
          "store": {
            "size": 0,
            "capacity": 500,
            "evicted": 0,
            "mean_gate": 0.0,
            "max_gate": 0.0,
            "mean_age": 0.0,
            "mean_tag_count": 0.0,
            "max_tag_count": 0,
            "mean_suppression": 0.0
          },
          "consolidation": {
            "n_patterns": 2082,
            "mean_strength": 0.06933914870023727,
            "max_strength": 8.663139343261719,
            "mean_u": [
              0.027130745351314545,
              0.04373220354318619,
              0.0487651489675045,
              0.044416893273591995,
              0.03292837738990784,
              0.017308257520198822
            ],
            "patterns_below_threshold": 0,
            "patterns_dead": 0,
            "step_count": 20
          },
          "memory_size": 2082
        },
        "phase4_stats_w4": {
          "retrievals": 1000,
          "candidates_total": 40,
          "store": {
            "size": 0,
            "capacity": 500,
            "evicted": 0,
            "mean_gate": 0.0,
            "max_gate": 0.0,
            "mean_age": 0.0,
            "mean_tag_count": 0.0,
            "max_tag_count": 0,
            "mean_suppression": 0.0
          },
          "consolidation": {
            "n_patterns": 1064,
            "mean_strength": 0.07784242182970047,
            "max_strength": 17.640363693237305,
            "mean_u": [
              0.03189053386449814,
              0.04881813004612923,
              0.052172064781188965,
              0.04651070758700371,
              0.03407508507370949,
              0.01780063286423683
            ],
            "patterns_below_threshold": 0,
            "patterns_dead": 0,
            "step_count": 20
          },
          "memory_size": 1064
        }
      },
      {
        "top1": 0.12244897959183673,
        "topk": 0.30272108843537415,
        "cap_t_03": 0.29931972789115646,
        "cap_t_05": 0.23469387755102042,
        "recall_at_k": {
          "1": 0.12244897959183673,
          "5": 0.23129251700680273,
          "10": 0.30272108843537415,
          "20": 0.3673469387755102,
          "50": 0.3673469387755102
        },
        "per_scale": {
          "2": {
            "mean_top_score": 0.9994147811211697,
            "mean_entropy": 0.6954047781269567,
            "metastable_rate": 0.0,
            "recall_at_k": {
              "1": 0.04081632653061224,
              "5": 0.25170068027210885,
              "10": 0.3333333333333333,
              "20": 0.4013605442176871,
              "50": 0.46258503401360546
            },
            "mean_settled_synergy_at_mask": -0.004529289434407362,
            "atom_pair_geometry": {
              "n_pairs": 100000,
              "mean": 0.35860527941077947,
              "std": 0.02882544429314986,
              "p95": 0.39637123048305506,
              "p99": 0.41300518721342083,
              "max": 0.580179750919342
            }
          },
          "3": {
            "mean_top_score": 0.9759820397613811,
            "mean_entropy": 0.7187522609217637,
            "metastable_rate": 0.0,
            "recall_at_k": {
              "1": 0.06802721088435375,
              "5": 0.21768707482993196,
              "10": 0.29591836734693877,
              "20": 0.3843537414965986,
              "50": 0.45918367346938777
            },
            "mean_settled_synergy_at_mask": 0.12122202050225923,
            "atom_pair_geometry": {
              "n_pairs": 100000,
              "mean": 0.35860527941077947,
              "std": 0.02882544429314986,
              "p95": 0.39637123048305506,
              "p99": 0.41300518721342083,
              "max": 0.580179750919342
            }
          },
          "4": {
            "mean_top_score": 0.964975391115461,
            "mean_entropy": 0.6282034408883984,
            "metastable_rate": 0.24829931972789115,
            "recall_at_k": {
              "1": 0.05442176870748299,
              "5": 0.19387755102040816,
              "10": 0.23809523809523808,
              "20": 0.30272108843537415,
              "50": 0.36394557823129253
            },
            "mean_settled_synergy_at_mask": 0.058761555176833326,
            "atom_pair_geometry": {
              "n_pairs": 100000,
              "mean": 0.35860527941077947,
              "std": 0.02882544429314986,
              "p95": 0.39637123048305506,
              "p99": 0.41300518721342083,
              "max": 0.580179750919342
            }
          }
        },
        "n": 294,
        "cues_seen": 1500,
        "condition": "phase4",
        "phase4_stats_w2": {
          "retrievals": 1500,
          "candidates_total": 31,
          "store": {
            "size": 0,
            "capacity": 500,
            "evicted": 0,
            "mean_gate": 0.0,
            "max_gate": 0.0,
            "mean_age": 0.0,
            "mean_tag_count": 0.0,
            "max_tag_count": 0,
            "mean_suppression": 0.0
          },
          "consolidation": {
            "n_patterns": 4127,
            "mean_strength": 0.039359476417303085,
            "max_strength": 13.804426193237305,
            "mean_u": [
              0.014741321094334126,
              0.02453381009399891,
              0.028706327080726624,
              0.02763797715306282,
              0.021611925214529037,
              0.011813705787062645
            ],
            "patterns_below_threshold": 0,
            "patterns_dead": 0,
            "step_count": 30
          },
          "memory_size": 4127
        },
        "phase4_stats_w3": {
          "retrievals": 1500,
          "candidates_total": 34,
          "store": {
            "size": 0,
            "capacity": 500,
            "evicted": 0,
            "mean_gate": 0.0,
            "max_gate": 0.0,
            "mean_age": 0.0,
            "mean_tag_count": 0.0,
            "max_tag_count": 0,
            "mean_suppression": 0.0
          },
          "consolidation": {
            "n_patterns": 2082,
            "mean_strength": 0.04421703517436981,
            "max_strength": 4.639983654022217,
            "mean_u": [
              0.01736046001315117,
              0.027449581772089005,
              0.030828891322016716,
              0.029086902737617493,
              0.022502001374959946,
              0.012234331108629704
            ],
            "patterns_below_threshold": 0,
            "patterns_dead": 0,
            "step_count": 30
          },
          "memory_size": 2082
        },
        "phase4_stats_w4": {
          "retrievals": 1500,
          "candidates_total": 40,
          "store": {
            "size": 0,
            "capacity": 500,
            "evicted": 0,
            "mean_gate": 0.0,
            "max_gate": 0.0,
            "mean_age": 0.0,
            "mean_tag_count": 0.0,
            "max_tag_count": 0,
            "mean_suppression": 0.0
          },
          "consolidation": {
            "n_patterns": 1064,
            "mean_strength": 0.05366366729140282,
            "max_strength": 20.145248413085938,
            "mean_u": [
              0.02244662120938301,
              0.03312427178025246,
              0.03497070446610451,
              0.03191571310162544,
              0.024237697944045067,
              0.013053251430392265
            ],
            "patterns_below_threshold": 0,
            "patterns_dead": 0,
            "step_count": 30
          },
          "memory_size": 1064
        }
      },
      {
        "top1": 0.09523809523809523,
        "topk": 0.29931972789115646,
        "cap_t_03": 0.29591836734693877,
        "cap_t_05": 0.23129251700680273,
        "recall_at_k": {
          "1": 0.09523809523809523,
          "5": 0.22108843537414966,
          "10": 0.29931972789115646,
          "20": 0.35034013605442177,
          "50": 0.35034013605442177
        },
        "per_scale": {
          "2": {
            "mean_top_score": 0.9994144806651031,
            "mean_entropy": 0.6943819956714604,
            "metastable_rate": 0.0,
            "recall_at_k": {
              "1": 0.04081632653061224,
              "5": 0.25510204081632654,
              "10": 0.3299319727891156,
              "20": 0.40476190476190477,
              "50": 0.46258503401360546
            },
            "mean_settled_synergy_at_mask": -0.010612025789260788,
            "atom_pair_geometry": {
              "n_pairs": 100000,
              "mean": 0.34239038572259245,
              "std": 0.027705249697179017,
              "p95": 0.37879347205162045,
              "p99": 0.3948320081830024,
              "max": 0.5542756915092468
            }
          },
          "3": {
            "mean_top_score": 0.9984875153116628,
            "mean_entropy": 0.7084069256068898,
            "metastable_rate": 0.0,
            "recall_at_k": {
              "1": 0.09183673469387756,
              "5": 0.22448979591836735,
              "10": 0.2857142857142857,
              "20": 0.3707482993197279,
              "50": 0.45918367346938777
            },
            "mean_settled_synergy_at_mask": 0.11416016071860609,
            "atom_pair_geometry": {
              "n_pairs": 100000,
              "mean": 0.34239038572259245,
              "std": 0.027705249697179017,
              "p95": 0.37879347205162045,
              "p99": 0.3948320081830024,
              "max": 0.5542756915092468
            }
          },
          "4": {
            "mean_top_score": 0.9644418946739768,
            "mean_entropy": 0.6213826474283828,
            "metastable_rate": 0.2857142857142857,
            "recall_at_k": {
              "1": 0.05442176870748299,
              "5": 0.19047619047619047,
              "10": 0.23809523809523808,
              "20": 0.29931972789115646,
              "50": 0.35714285714285715
            },
            "mean_settled_synergy_at_mask": 0.058399630644751496,
            "atom_pair_geometry": {
              "n_pairs": 100000,
              "mean": 0.34239038572259245,
              "std": 0.027705249697179017,
              "p95": 0.37879347205162045,
              "p99": 0.3948320081830024,
              "max": 0.5542756915092468
            }
          }
        },
        "n": 294,
        "cues_seen": 2000,
        "condition": "phase4",
        "phase4_stats_w2": {
          "retrievals": 2000,
          "candidates_total": 31,
          "store": {
            "size": 0,
            "capacity": 500,
            "evicted": 0,
            "mean_gate": 0.0,
            "max_gate": 0.0,
            "mean_age": 0.0,
            "mean_tag_count": 0.0,
            "max_tag_count": 0,
            "mean_suppression": 0.0
          },
          "consolidation": {
            "n_patterns": 4127,
            "mean_strength": 0.025712793692946434,
            "max_strength": 16.593114852905273,
            "mean_u": [
              0.009880763478577137,
              0.015940846875309944,
              0.01828858070075512,
              0.017549559473991394,
              0.013758964836597443,
              0.0075465920381248
            ],
            "patterns_below_threshold": 0,
            "patterns_dead": 0,
            "step_count": 40
          },
          "memory_size": 4127
        },
        "phase4_stats_w3": {
          "retrievals": 2000,
          "candidates_total": 36,
          "store": {
            "size": 0,
            "capacity": 500,
            "evicted": 0,
            "mean_gate": 0.0,
            "max_gate": 0.0,
            "mean_age": 0.0,
            "mean_tag_count": 0.0,
            "max_tag_count": 0,
            "mean_suppression": 0.0
          },
          "consolidation": {
            "n_patterns": 2084,
            "mean_strength": 0.03105405904352665,
            "max_strength": 13.279071807861328,
            "mean_u": [
              0.012704321183264256,
              0.019166061654686928,
              0.020721036940813065,
              0.019257014617323875,
              0.014835950918495655,
              0.008066360838711262
            ],
            "patterns_below_threshold": 0,
            "patterns_dead": 0,
            "step_count": 40
          },
          "memory_size": 2084
        },
        "phase4_stats_w4": {
          "retrievals": 2000,
          "candidates_total": 40,
          "store": {
            "size": 0,
            "capacity": 500,
            "evicted": 0,
            "mean_gate": 0.0,
            "max_gate": 0.0,
            "mean_age": 0.0,
            "mean_tag_count": 0.0,
            "max_tag_count": 0,
            "mean_suppression": 0.0
          },
          "consolidation": {
            "n_patterns": 1064,
            "mean_strength": 0.04089772328734398,
            "max_strength": 20.089569091796875,
            "mean_u": [
              0.017893662676215172,
              0.025082161650061607,
              0.02523420751094818,
              0.022502990439534187,
              0.0169230904430151,
              0.009083706885576248
            ],
            "patterns_below_threshold": 0,
            "patterns_dead": 0,
            "step_count": 40
          },
          "memory_size": 1064
        }
      }
    ]
  }
}