{
  "config": {
    "dim": 4096,
    "device": null,
    "max_vocab": 2048,
    "corpus_source": "wikitext",
    "wikitext_name": "wikitext-2-raw-v1",
    "seed": 17,
    "codebook_path": "reports/phase3c_reconstruction/phase3c_codebook_reconstruction.pt",
    "scale_landscape": "2:4096,3:2048,4:1024",
    "eval_window_size": 8,
    "mask_position": "center",
    "beta": 10.0,
    "decode_k": 10,
    "rank_k": 50,
    "atom_sample_pairs": 100000,
    "n_cues": 2000,
    "checkpoint_every": 500,
    "drift_magnitude": 0.5,
    "test_samples": 400,
    "replay_every": 50,
    "replay_batch_size": 10,
    "store_threshold": 0.05,
    "resolve_threshold": 0.7,
    "store_capacity": 500,
    "consolidation_m": 6,
    "consolidation_alpha": 0.25,
    "novelty_strength": 1.0,
    "retrieval_gain": 0.1,
    "death_window": 1000,
    "death_threshold": 0.005,
    "reencode_every": 100,
    "output_dir": "reports/phase4_drift_0p50"
  },
  "results": {
    "baseline": [
      {
        "top1": 0.12244897959183673,
        "topk": 0.30952380952380953,
        "cap_t_03": 0.30952380952380953,
        "cap_t_05": 0.2755102040816326,
        "recall_at_k": {
          "1": 0.12244897959183673,
          "5": 0.23809523809523808,
          "10": 0.30952380952380953,
          "20": 0.3741496598639456,
          "50": 0.3877551020408163
        },
        "per_scale": {
          "2": {
            "mean_top_score": 0.9543128611684657,
            "mean_entropy": 0.7296215084945263,
            "metastable_rate": 0.4421768707482993,
            "recall_at_k": {
              "1": 0.12244897959183673,
              "5": 0.24489795918367346,
              "10": 0.3333333333333333,
              "20": 0.3979591836734694,
              "50": 0.47278911564625853
            },
            "mean_settled_synergy_at_mask": -0.006281335044614211,
            "atom_pair_geometry": {
              "n_pairs": 100000,
              "mean": 0.4102353788114339,
              "std": 0.03225641030834313,
              "p95": 0.45158186852931975,
              "p99": 0.4692427709698676,
              "max": 0.6612575054168701
            }
          },
          "3": {
            "mean_top_score": 0.8876099028960377,
            "mean_entropy": 0.7856069853922136,
            "metastable_rate": 0.9931972789115646,
            "recall_at_k": {
              "1": 0.09863945578231292,
              "5": 0.22108843537414966,
              "10": 0.3129251700680272,
              "20": 0.38095238095238093,
              "50": 0.4421768707482993
            },
            "mean_settled_synergy_at_mask": 0.14807024743759586,
            "atom_pair_geometry": {
              "n_pairs": 100000,
              "mean": 0.4102353788114339,
              "std": 0.03225641030834313,
              "p95": 0.45158186852931975,
              "p99": 0.4692427709698676,
              "max": 0.6612575054168701
            }
          },
          "4": {
            "mean_top_score": 0.8327003861365675,
            "mean_entropy": 0.7450994307897529,
            "metastable_rate": 0.717687074829932,
            "recall_at_k": {
              "1": 0.07482993197278912,
              "5": 0.19387755102040816,
              "10": 0.22789115646258504,
              "20": 0.29931972789115646,
              "50": 0.36394557823129253
            },
            "mean_settled_synergy_at_mask": 0.10591754989621711,
            "atom_pair_geometry": {
              "n_pairs": 100000,
              "mean": 0.4102353788114339,
              "std": 0.03225641030834313,
              "p95": 0.45158186852931975,
              "p99": 0.4692427709698676,
              "max": 0.6612575054168701
            }
          }
        },
        "n": 294,
        "cues_seen": 0,
        "condition": "baseline"
      },
      {
        "top1": 0.12244897959183673,
        "topk": 0.3231292517006803,
        "cap_t_03": 0.3231292517006803,
        "cap_t_05": 0.25510204081632654,
        "recall_at_k": {
          "1": 0.12244897959183673,
          "5": 0.22789115646258504,
          "10": 0.3231292517006803,
          "20": 0.391156462585034,
          "50": 0.391156462585034
        },
        "per_scale": {
          "2": {
            "mean_top_score": 0.9352088069834676,
            "mean_entropy": 0.7374383026645297,
            "metastable_rate": 0.4523809523809524,
            "recall_at_k": {
              "1": 0.12244897959183673,
              "5": 0.24149659863945577,
              "10": 0.3231292517006803,
              "20": 0.4013605442176871,
              "50": 0.46938775510204084
            },
            "mean_settled_synergy_at_mask": 0.057550158222573394,
            "atom_pair_geometry": {
              "n_pairs": 100000,
              "mean": 0.36102866776414216,
              "std": 0.02924345974681508,
              "p95": 0.39920960664749144,
              "p99": 0.41659660130739207,
              "max": 0.5864728093147278
            }
          },
          "3": {
            "mean_top_score": 0.8887230013908983,
            "mean_entropy": 0.7846446416410459,
            "metastable_rate": 0.9931972789115646,
            "recall_at_k": {
              "1": 0.09863945578231292,
              "5": 0.22448979591836735,
              "10": 0.30612244897959184,
              "20": 0.3843537414965986,
              "50": 0.445578231292517
            },
            "mean_settled_synergy_at_mask": 0.14410900934575582,
            "atom_pair_geometry": {
              "n_pairs": 100000,
              "mean": 0.36102866776414216,
              "std": 0.02924345974681508,
              "p95": 0.39920960664749144,
              "p99": 0.41659660130739207,
              "max": 0.5864728093147278
            }
          },
          "4": {
            "mean_top_score": 0.8328034533124392,
            "mean_entropy": 0.7450472234057731,
            "metastable_rate": 0.7244897959183674,
            "recall_at_k": {
              "1": 0.07482993197278912,
              "5": 0.19047619047619047,
              "10": 0.23129251700680273,
              "20": 0.2891156462585034,
              "50": 0.3707482993197279
            },
            "mean_settled_synergy_at_mask": 0.0981566954628235,
            "atom_pair_geometry": {
              "n_pairs": 100000,
              "mean": 0.36102866776414216,
              "std": 0.02924345974681508,
              "p95": 0.39920960664749144,
              "p99": 0.41659660130739207,
              "max": 0.5864728093147278
            }
          }
        },
        "n": 294,
        "cues_seen": 500,
        "condition": "baseline"
      },
      {
        "top1": 0.08843537414965986,
        "topk": 0.3129251700680272,
        "cap_t_03": 0.282312925170068,
        "cap_t_05": 0.20068027210884354,
        "recall_at_k": {
          "1": 0.08843537414965986,
          "5": 0.22789115646258504,
          "10": 0.3129251700680272,
          "20": 0.36394557823129253,
          "50": 0.36394557823129253
        },
        "per_scale": {
          "2": {
            "mean_top_score": 0.9997542230855851,
            "mean_entropy": 0.6845814612041525,
            "metastable_rate": 0.0,
            "recall_at_k": {
              "1": 0.04081632653061224,
              "5": 0.24829931972789115,
              "10": 0.3333333333333333,
              "20": 0.4013605442176871,
              "50": 0.4387755102040816
            },
            "mean_settled_synergy_at_mask": 0.0016571951014002417,
            "atom_pair_geometry": {
              "n_pairs": 100000,
              "mean": 0.31511196334801617,
              "std": 0.026122245863016532,
              "p95": 0.34986031204462054,
              "p99": 0.36537239819765077,
              "max": 0.5074440240859985
            }
          },
          "3": {
            "mean_top_score": 0.8937808885460808,
            "mean_entropy": 0.7749824503652093,
            "metastable_rate": 0.9693877551020408,
            "recall_at_k": {
              "1": 0.07482993197278912,
              "5": 0.22108843537414966,
              "10": 0.2857142857142857,
              "20": 0.3741496598639456,
              "50": 0.4421768707482993
            },
            "mean_settled_synergy_at_mask": 0.12303413255583673,
            "atom_pair_geometry": {
              "n_pairs": 100000,
              "mean": 0.31511196334801617,
              "std": 0.026122245863016532,
              "p95": 0.34986031204462054,
              "p99": 0.36537239819765077,
              "max": 0.5074440240859985
            }
          },
          "4": {
            "mean_top_score": 0.8494215552904167,
            "mean_entropy": 0.7178331700717511,
            "metastable_rate": 0.6938775510204082,
            "recall_at_k": {
              "1": 0.05782312925170068,
              "5": 0.1870748299319728,
              "10": 0.23129251700680273,
              "20": 0.2857142857142857,
              "50": 0.35374149659863946
            },
            "mean_settled_synergy_at_mask": 0.09040636085068846,
            "atom_pair_geometry": {
              "n_pairs": 100000,
              "mean": 0.31511196334801617,
              "std": 0.026122245863016532,
              "p95": 0.34986031204462054,
              "p99": 0.36537239819765077,
              "max": 0.5074440240859985
            }
          }
        },
        "n": 294,
        "cues_seen": 1000,
        "condition": "baseline"
      },
      {
        "top1": 0.09183673469387756,
        "topk": 0.3129251700680272,
        "cap_t_03": 0.272108843537415,
        "cap_t_05": 0.10204081632653061,
        "recall_at_k": {
          "1": 0.09183673469387756,
          "5": 0.2108843537414966,
          "10": 0.3129251700680272,
          "20": 0.35034013605442177,
          "50": 0.35374149659863946
        },
        "per_scale": {
          "2": {
            "mean_top_score": 0.998976431330856,
            "mean_entropy": 0.6843496451572496,
            "metastable_rate": 0.006802721088435374,
            "recall_at_k": {
              "1": 0.04081632653061224,
              "5": 0.24149659863945577,
              "10": 0.3333333333333333,
              "20": 0.3945578231292517,
              "50": 0.45918367346938777
            },
            "mean_settled_synergy_at_mask": -0.019825603818476555,
            "atom_pair_geometry": {
              "n_pairs": 100000,
              "mean": 0.274955799985677,
              "std": 0.023380140910337154,
              "p95": 0.3066042363643646,
              "p99": 0.32025651246309267,
              "max": 0.4471096098423004
            }
          },
          "3": {
            "mean_top_score": 0.9283864700875315,
            "mean_entropy": 0.720177351212015,
            "metastable_rate": 0.5306122448979592,
            "recall_at_k": {
              "1": 0.0782312925170068,
              "5": 0.21428571428571427,
              "10": 0.282312925170068,
              "20": 0.36394557823129253,
              "50": 0.46258503401360546
            },
            "mean_settled_synergy_at_mask": 0.10270109473249311,
            "atom_pair_geometry": {
              "n_pairs": 100000,
              "mean": 0.274955799985677,
              "std": 0.023380140910337154,
              "p95": 0.3066042363643646,
              "p99": 0.32025651246309267,
              "max": 0.4471096098423004
            }
          },
          "4": {
            "mean_top_score": 0.8982465252989814,
            "mean_entropy": 0.6570503740083604,
            "metastable_rate": 0.5510204081632653,
            "recall_at_k": {
              "1": 0.05442176870748299,
              "5": 0.15306122448979592,
              "10": 0.19047619047619047,
              "20": 0.22789115646258504,
              "50": 0.2789115646258503
            },
            "mean_settled_synergy_at_mask": 0.0719859393315111,
            "atom_pair_geometry": {
              "n_pairs": 100000,
              "mean": 0.274955799985677,
              "std": 0.023380140910337154,
              "p95": 0.3066042363643646,
              "p99": 0.32025651246309267,
              "max": 0.4471096098423004
            }
          }
        },
        "n": 294,
        "cues_seen": 1500,
        "condition": "baseline"
      },
      {
        "top1": 0.07142857142857142,
        "topk": 0.3333333333333333,
        "cap_t_03": 0.22448979591836735,
        "cap_t_05": 0.05782312925170068,
        "recall_at_k": {
          "1": 0.07142857142857142,
          "5": 0.23809523809523808,
          "10": 0.3333333333333333,
          "20": 0.3469387755102041,
          "50": 0.3469387755102041
        },
        "per_scale": {
          "2": {
            "mean_top_score": 0.9999084190851977,
            "mean_entropy": 0.6799878206382803,
            "metastable_rate": 0.0,
            "recall_at_k": {
              "1": 0.04081632653061224,
              "5": 0.24489795918367346,
              "10": 0.3333333333333333,
              "20": 0.3877551020408163,
              "50": 0.46598639455782315
            },
            "mean_settled_synergy_at_mask": -0.023868721193510432,
            "atom_pair_geometry": {
              "n_pairs": 100000,
              "mean": 0.24001894973799587,
              "std": 0.02110469723197096,
              "p95": 0.26907471120357507,
              "p99": 0.2814843493700027,
              "max": 0.39571982622146606
            }
          },
          "3": {
            "mean_top_score": 0.978069672981898,
            "mean_entropy": 0.6235882915607115,
            "metastable_rate": 0.08503401360544217,
            "recall_at_k": {
              "1": 0.05782312925170068,
              "5": 0.20408163265306123,
              "10": 0.29931972789115646,
              "20": 0.3741496598639456,
              "50": 0.4421768707482993
            },
            "mean_settled_synergy_at_mask": 0.05632607666237064,
            "atom_pair_geometry": {
              "n_pairs": 100000,
              "mean": 0.24001894973799587,
              "std": 0.02110469723197096,
              "p95": 0.26907471120357507,
              "p99": 0.2814843493700027,
              "max": 0.39571982622146606
            }
          },
          "4": {
            "mean_top_score": 0.9230607176313594,
            "mean_entropy": 0.6099238440293033,
            "metastable_rate": 0.5034013605442177,
            "recall_at_k": {
              "1": 0.061224489795918366,
              "5": 0.14625850340136054,
              "10": 0.1870748299319728,
              "20": 0.23809523809523808,
              "50": 0.282312925170068
            },
            "mean_settled_synergy_at_mask": 0.06843576839765483,
            "atom_pair_geometry": {
              "n_pairs": 100000,
              "mean": 0.24001894973799587,
              "std": 0.02110469723197096,
              "p95": 0.26907471120357507,
              "p99": 0.2814843493700027,
              "max": 0.39571982622146606
            }
          }
        },
        "n": 294,
        "cues_seen": 2000,
        "condition": "baseline"
      }
    ],
    "phase4": [
      {
        "top1": 0.12244897959183673,
        "topk": 0.30952380952380953,
        "cap_t_03": 0.30952380952380953,
        "cap_t_05": 0.2755102040816326,
        "recall_at_k": {
          "1": 0.12244897959183673,
          "5": 0.23809523809523808,
          "10": 0.30952380952380953,
          "20": 0.3741496598639456,
          "50": 0.3877551020408163
        },
        "per_scale": {
          "2": {
            "mean_top_score": 0.9543128611684657,
            "mean_entropy": 0.7296215084945263,
            "metastable_rate": 0.4421768707482993,
            "recall_at_k": {
              "1": 0.12244897959183673,
              "5": 0.24489795918367346,
              "10": 0.3333333333333333,
              "20": 0.3979591836734694,
              "50": 0.47278911564625853
            },
            "mean_settled_synergy_at_mask": -0.006281335044614211,
            "atom_pair_geometry": {
              "n_pairs": 100000,
              "mean": 0.4102353788114339,
              "std": 0.03225641030834313,
              "p95": 0.45158186852931975,
              "p99": 0.4692427709698676,
              "max": 0.6612575054168701
            }
          },
          "3": {
            "mean_top_score": 0.8876099028960377,
            "mean_entropy": 0.7856069853922136,
            "metastable_rate": 0.9931972789115646,
            "recall_at_k": {
              "1": 0.09863945578231292,
              "5": 0.22108843537414966,
              "10": 0.3129251700680272,
              "20": 0.38095238095238093,
              "50": 0.4421768707482993
            },
            "mean_settled_synergy_at_mask": 0.14807024743759586,
            "atom_pair_geometry": {
              "n_pairs": 100000,
              "mean": 0.4102353788114339,
              "std": 0.03225641030834313,
              "p95": 0.45158186852931975,
              "p99": 0.4692427709698676,
              "max": 0.6612575054168701
            }
          },
          "4": {
            "mean_top_score": 0.8327003861365675,
            "mean_entropy": 0.7450994307897529,
            "metastable_rate": 0.717687074829932,
            "recall_at_k": {
              "1": 0.07482993197278912,
              "5": 0.19387755102040816,
              "10": 0.22789115646258504,
              "20": 0.29931972789115646,
              "50": 0.36394557823129253
            },
            "mean_settled_synergy_at_mask": 0.10591754989621711,
            "atom_pair_geometry": {
              "n_pairs": 100000,
              "mean": 0.4102353788114339,
              "std": 0.03225641030834313,
              "p95": 0.45158186852931975,
              "p99": 0.4692427709698676,
              "max": 0.6612575054168701
            }
          }
        },
        "n": 294,
        "cues_seen": 0,
        "condition": "phase4",
        "phase4_stats_w2": {
          "retrievals": 0,
          "candidates_total": 0,
          "store": {
            "size": 0,
            "capacity": 500,
            "evicted": 0,
            "mean_gate": 0.0,
            "max_gate": 0.0,
            "mean_age": 0.0,
            "mean_tag_count": 0.0,
            "max_tag_count": 0,
            "mean_suppression": 0.0
          },
          "consolidation": {
            "n_patterns": 4096,
            "mean_strength": 1.0,
            "max_strength": 1.0,
            "mean_u": [
              1.0,
              0.0,
              0.0,
              0.0,
              0.0,
              0.0
            ],
            "patterns_below_threshold": 0,
            "patterns_dead": 0,
            "step_count": 0
          },
          "memory_size": 4096
        },
        "phase4_stats_w3": {
          "retrievals": 0,
          "candidates_total": 0,
          "store": {
            "size": 0,
            "capacity": 500,
            "evicted": 0,
            "mean_gate": 0.0,
            "max_gate": 0.0,
            "mean_age": 0.0,
            "mean_tag_count": 0.0,
            "max_tag_count": 0,
            "mean_suppression": 0.0
          },
          "consolidation": {
            "n_patterns": 2048,
            "mean_strength": 1.0,
            "max_strength": 1.0,
            "mean_u": [
              1.0,
              0.0,
              0.0,
              0.0,
              0.0,
              0.0
            ],
            "patterns_below_threshold": 0,
            "patterns_dead": 0,
            "step_count": 0
          },
          "memory_size": 2048
        },
        "phase4_stats_w4": {
          "retrievals": 0,
          "candidates_total": 0,
          "store": {
            "size": 0,
            "capacity": 500,
            "evicted": 0,
            "mean_gate": 0.0,
            "max_gate": 0.0,
            "mean_age": 0.0,
            "mean_tag_count": 0.0,
            "max_tag_count": 0,
            "mean_suppression": 0.0
          },
          "consolidation": {
            "n_patterns": 1024,
            "mean_strength": 1.0,
            "max_strength": 1.0,
            "mean_u": [
              1.0,
              0.0,
              0.0,
              0.0,
              0.0,
              0.0
            ],
            "patterns_below_threshold": 0,
            "patterns_dead": 0,
            "step_count": 0
          },
          "memory_size": 1024
        }
      },
      {
        "top1": 0.12244897959183673,
        "topk": 0.30612244897959184,
        "cap_t_03": 0.30272108843537415,
        "cap_t_05": 0.23469387755102042,
        "recall_at_k": {
          "1": 0.12244897959183673,
          "5": 0.23129251700680273,
          "10": 0.30612244897959184,
          "20": 0.37755102040816324,
          "50": 0.3877551020408163
        },
        "per_scale": {
          "2": {
            "mean_top_score": 0.9996220412708464,
            "mean_entropy": 0.6986546875262747,
            "metastable_rate": 0.0,
            "recall_at_k": {
              "1": 0.12244897959183673,
              "5": 0.24829931972789115,
              "10": 0.3333333333333333,
              "20": 0.391156462585034,
              "50": 0.4489795918367347
            },
            "mean_settled_synergy_at_mask": 0.0033119916583278348,
            "atom_pair_geometry": {
              "n_pairs": 100000,
              "mean": 0.36102866776414216,
              "std": 0.02924345974681508,
              "p95": 0.39920960664749144,
              "p99": 0.41659660130739207,
              "max": 0.5864728093147278
            }
          },
          "3": {
            "mean_top_score": 0.9999986120632717,
            "mean_entropy": 0.7306525180128967,
            "metastable_rate": 0.0,
            "recall_at_k": {
              "1": 0.09183673469387756,
              "5": 0.22448979591836735,
              "10": 0.30612244897959184,
              "20": 0.3843537414965986,
              "50": 0.445578231292517
            },
            "mean_settled_synergy_at_mask": 0.1261315472712297,
            "atom_pair_geometry": {
              "n_pairs": 100000,
              "mean": 0.36102866776414216,
              "std": 0.02924345974681508,
              "p95": 0.39920960664749144,
              "p99": 0.41659660130739207,
              "max": 0.5864728093147278
            }
          },
          "4": {
            "mean_top_score": 0.9665900935121134,
            "mean_entropy": 0.6429834167162577,
            "metastable_rate": 0.24489795918367346,
            "recall_at_k": {
              "1": 0.05782312925170068,
              "5": 0.2108843537414966,
              "10": 0.2653061224489796,
              "20": 0.3333333333333333,
              "50": 0.40476190476190477
            },
            "mean_settled_synergy_at_mask": 0.059613726406317,
            "atom_pair_geometry": {
              "n_pairs": 100000,
              "mean": 0.36102866776414216,
              "std": 0.02924345974681508,
              "p95": 0.39920960664749144,
              "p99": 0.41659660130739207,
              "max": 0.5864728093147278
            }
          }
        },
        "n": 294,
        "cues_seen": 500,
        "condition": "phase4",
        "phase4_stats_w2": {
          "retrievals": 500,
          "candidates_total": 30,
          "store": {
            "size": 0,
            "capacity": 500,
            "evicted": 0,
            "mean_gate": 0.0,
            "max_gate": 0.0,
            "mean_age": 0.0,
            "mean_tag_count": 0.0,
            "max_tag_count": 0,
            "mean_suppression": 0.0
          },
          "consolidation": {
            "n_patterns": 4126,
            "mean_strength": 0.13326223194599152,
            "max_strength": 3.2642765045166016,
            "mean_u": [
              0.05819894000887871,
              0.08828923851251602,
              0.08422782272100449,
              0.059573013335466385,
              0.0323098823428154,
              0.012663357891142368
            ],
            "patterns_below_threshold": 0,
            "patterns_dead": 0,
            "step_count": 10
          },
          "memory_size": 4126
        },
        "phase4_stats_w3": {
          "retrievals": 500,
          "candidates_total": 34,
          "store": {
            "size": 0,
            "capacity": 500,
            "evicted": 0,
            "mean_gate": 0.0,
            "max_gate": 0.0,
            "mean_age": 0.0,
            "mean_tag_count": 0.0,
            "max_tag_count": 0,
            "mean_suppression": 0.0
          },
          "consolidation": {
            "n_patterns": 2082,
            "mean_strength": 0.13678531348705292,
            "max_strength": 13.193732261657715,
            "mean_u": [
              0.06035618111491203,
              0.09036001563072205,
              0.08529962599277496,
              0.06000695377588272,
              0.03243272006511688,
              0.01268182322382927
            ],
            "patterns_below_threshold": 0,
            "patterns_dead": 0,
            "step_count": 10
          },
          "memory_size": 2082
        },
        "phase4_stats_w4": {
          "retrievals": 500,
          "candidates_total": 40,
          "store": {
            "size": 0,
            "capacity": 500,
            "evicted": 0,
            "mean_gate": 0.0,
            "max_gate": 0.0,
            "mean_age": 0.0,
            "mean_tag_count": 0.0,
            "max_tag_count": 0,
            "mean_suppression": 0.0
          },
          "consolidation": {
            "n_patterns": 1064,
            "mean_strength": 0.1437855213880539,
            "max_strength": 13.18115234375,
            "mean_u": [
              0.06464007496833801,
              0.09449472278356552,
              0.08743293583393097,
              0.06083153560757637,
              0.03262927755713463,
              0.012690371833741665
            ],
            "patterns_below_threshold": 0,
            "patterns_dead": 0,
            "step_count": 10
          },
          "memory_size": 1064
        }
      },
      {
        "top1": 0.08843537414965986,
        "topk": 0.3197278911564626,
        "cap_t_03": 0.29591836734693877,
        "cap_t_05": 0.20748299319727892,
        "recall_at_k": {
          "1": 0.08843537414965986,
          "5": 0.22789115646258504,
          "10": 0.3197278911564626,
          "20": 0.35714285714285715,
          "50": 0.35714285714285715
        },
        "per_scale": {
          "2": {
            "mean_top_score": 0.9995682829496811,
            "mean_entropy": 0.6918366683178208,
            "metastable_rate": 0.0,
            "recall_at_k": {
              "1": 0.04081632653061224,
              "5": 0.24829931972789115,
              "10": 0.3333333333333333,
              "20": 0.4013605442176871,
              "50": 0.4387755102040816
            },
            "mean_settled_synergy_at_mask": 0.0015305239413421425,
            "atom_pair_geometry": {
              "n_pairs": 100000,
              "mean": 0.31511196334801617,
              "std": 0.026122245863016532,
              "p95": 0.34986031204462054,
              "p99": 0.36537239819765077,
              "max": 0.5074440240859985
            }
          },
          "3": {
            "mean_top_score": 0.9984547834412582,
            "mean_entropy": 0.7100062232439209,
            "metastable_rate": 0.0,
            "recall_at_k": {
              "1": 0.06802721088435375,
              "5": 0.22108843537414966,
              "10": 0.2857142857142857,
              "20": 0.3741496598639456,
              "50": 0.4421768707482993
            },
            "mean_settled_synergy_at_mask": 0.11200068421308648,
            "atom_pair_geometry": {
              "n_pairs": 100000,
              "mean": 0.31511196334801617,
              "std": 0.026122245863016532,
              "p95": 0.34986031204462054,
              "p99": 0.36537239819765077,
              "max": 0.5074440240859985
            }
          },
          "4": {
            "mean_top_score": 0.9704690076866929,
            "mean_entropy": 0.6173620317257992,
            "metastable_rate": 0.22448979591836735,
            "recall_at_k": {
              "1": 0.05782312925170068,
              "5": 0.20068027210884354,
              "10": 0.24829931972789115,
              "20": 0.3163265306122449,
              "50": 0.3843537414965986
            },
            "mean_settled_synergy_at_mask": 0.047717811991967465,
            "atom_pair_geometry": {
              "n_pairs": 100000,
              "mean": 0.31511196334801617,
              "std": 0.026122245863016532,
              "p95": 0.34986031204462054,
              "p99": 0.36537239819765077,
              "max": 0.5074440240859985
            }
          }
        },
        "n": 294,
        "cues_seen": 1000,
        "condition": "phase4",
        "phase4_stats_w2": {
          "retrievals": 1000,
          "candidates_total": 31,
          "store": {
            "size": 0,
            "capacity": 500,
            "evicted": 0,
            "mean_gate": 0.0,
            "max_gate": 0.0,
            "mean_age": 0.0,
            "mean_tag_count": 0.0,
            "max_tag_count": 0,
            "mean_suppression": 0.0
          },
          "consolidation": {
            "n_patterns": 4127,
            "mean_strength": 0.06501585245132446,
            "max_strength": 9.840928077697754,
            "mean_u": [
              0.024710923433303833,
              0.041151292622089386,
              0.04703177884221077,
              0.0433412604033947,
              0.03233335167169571,
              0.017050959169864655
            ],
            "patterns_below_threshold": 0,
            "patterns_dead": 0,
            "step_count": 20
          },
          "memory_size": 4127
        },
        "phase4_stats_w3": {
          "retrievals": 1000,
          "candidates_total": 35,
          "store": {
            "size": 0,
            "capacity": 500,
            "evicted": 0,
            "mean_gate": 0.0,
            "max_gate": 0.0,
            "mean_age": 0.0,
            "mean_tag_count": 0.0,
            "max_tag_count": 0,
            "mean_suppression": 0.0
          },
          "consolidation": {
            "n_patterns": 2083,
            "mean_strength": 0.06960590928792953,
            "max_strength": 8.829265594482422,
            "mean_u": [
              0.027357758954167366,
              0.043831221759319305,
              0.04874172806739807,
              0.0443955697119236,
              0.032912567257881165,
              0.017299946397542953
            ],
            "patterns_below_threshold": 0,
            "patterns_dead": 0,
            "step_count": 20
          },
          "memory_size": 2083
        },
        "phase4_stats_w4": {
          "retrievals": 1000,
          "candidates_total": 40,
          "store": {
            "size": 0,
            "capacity": 500,
            "evicted": 0,
            "mean_gate": 0.0,
            "max_gate": 0.0,
            "mean_age": 0.0,
            "mean_tag_count": 0.0,
            "max_tag_count": 0,
            "mean_suppression": 0.0
          },
          "consolidation": {
            "n_patterns": 1064,
            "mean_strength": 0.07784241437911987,
            "max_strength": 14.552839279174805,
            "mean_u": [
              0.03189052641391754,
              0.04881812259554863,
              0.052172064781188965,
              0.04651070386171341,
              0.03407508507370949,
              0.01780063286423683
            ],
            "patterns_below_threshold": 0,
            "patterns_dead": 0,
            "step_count": 20
          },
          "memory_size": 1064
        }
      },
      {
        "top1": 0.08163265306122448,
        "topk": 0.3129251700680272,
        "cap_t_03": 0.2891156462585034,
        "cap_t_05": 0.16666666666666666,
        "recall_at_k": {
          "1": 0.08163265306122448,
          "5": 0.21768707482993196,
          "10": 0.3129251700680272,
          "20": 0.35034013605442177,
          "50": 0.35034013605442177
        },
        "per_scale": {
          "2": {
            "mean_top_score": 0.9997323234470523,
            "mean_entropy": 0.6899686613861395,
            "metastable_rate": 0.0,
            "recall_at_k": {
              "1": 0.04081632653061224,
              "5": 0.24149659863945577,
              "10": 0.3333333333333333,
              "20": 0.3945578231292517,
              "50": 0.45918367346938777
            },
            "mean_settled_synergy_at_mask": -0.01944796647005366,
            "atom_pair_geometry": {
              "n_pairs": 100000,
              "mean": 0.274955799985677,
              "std": 0.023380140910337154,
              "p95": 0.3066042363643646,
              "p99": 0.32025651246309267,
              "max": 0.4471096098423004
            }
          },
          "3": {
            "mean_top_score": 0.9697279917950533,
            "mean_entropy": 0.6803971597937499,
            "metastable_rate": 0.38095238095238093,
            "recall_at_k": {
              "1": 0.06802721088435375,
              "5": 0.22108843537414966,
              "10": 0.282312925170068,
              "20": 0.38095238095238093,
              "50": 0.46598639455782315
            },
            "mean_settled_synergy_at_mask": 0.09764914329402896,
            "atom_pair_geometry": {
              "n_pairs": 100000,
              "mean": 0.274955799985677,
              "std": 0.023380140910337154,
              "p95": 0.3066042363643646,
              "p99": 0.32025651246309267,
              "max": 0.4471096098423004
            }
          },
          "4": {
            "mean_top_score": 0.9830497612758559,
            "mean_entropy": 0.5811303716127564,
            "metastable_rate": 0.1360544217687075,
            "recall_at_k": {
              "1": 0.05442176870748299,
              "5": 0.19727891156462585,
              "10": 0.24829931972789115,
              "20": 0.30952380952380953,
              "50": 0.36054421768707484
            },
            "mean_settled_synergy_at_mask": 0.03446295400796344,
            "atom_pair_geometry": {
              "n_pairs": 100000,
              "mean": 0.274955799985677,
              "std": 0.023380140910337154,
              "p95": 0.3066042363643646,
              "p99": 0.32025651246309267,
              "max": 0.4471096098423004
            }
          }
        },
        "n": 294,
        "cues_seen": 1500,
        "condition": "phase4",
        "phase4_stats_w2": {
          "retrievals": 1500,
          "candidates_total": 31,
          "store": {
            "size": 0,
            "capacity": 500,
            "evicted": 0,
            "mean_gate": 0.0,
            "max_gate": 0.0,
            "mean_age": 0.0,
            "mean_tag_count": 0.0,
            "max_tag_count": 0,
            "mean_suppression": 0.0
          },
          "consolidation": {
            "n_patterns": 4127,
            "mean_strength": 0.03935019671916962,
            "max_strength": 14.55242919921875,
            "mean_u": [
              0.014736486598849297,
              0.024527322500944138,
              0.028701771050691605,
              0.027636714279651642,
              0.021612850949168205,
              0.011814831756055355
            ],
            "patterns_below_threshold": 0,
            "patterns_dead": 0,
            "step_count": 30
          },
          "memory_size": 4127
        },
        "phase4_stats_w3": {
          "retrievals": 1500,
          "candidates_total": 35,
          "store": {
            "size": 0,
            "capacity": 500,
            "evicted": 0,
            "mean_gate": 0.0,
            "max_gate": 0.0,
            "mean_age": 0.0,
            "mean_tag_count": 0.0,
            "max_tag_count": 0,
            "mean_suppression": 0.0
          },
          "consolidation": {
            "n_patterns": 2083,
            "mean_strength": 0.0442524291574955,
            "max_strength": 11.789688110351562,
            "mean_u": [
              0.017375944182276726,
              0.027473824098706245,
              0.03085150197148323,
              0.029100971296429634,
              0.022507531568408012,
              0.012235349044203758
            ],
            "patterns_below_threshold": 0,
            "patterns_dead": 0,
            "step_count": 30
          },
          "memory_size": 2083
        },
        "phase4_stats_w4": {
          "retrievals": 1500,
          "candidates_total": 40,
          "store": {
            "size": 0,
            "capacity": 500,
            "evicted": 0,
            "mean_gate": 0.0,
            "max_gate": 0.0,
            "mean_age": 0.0,
            "mean_tag_count": 0.0,
            "max_tag_count": 0,
            "mean_suppression": 0.0
          },
          "consolidation": {
            "n_patterns": 1064,
            "mean_strength": 0.05366365611553192,
            "max_strength": 18.743629455566406,
            "mean_u": [
              0.022446617484092712,
              0.03312426805496216,
              0.03497070074081421,
              0.031915709376335144,
              0.024237696081399918,
              0.01305325049906969
            ],
            "patterns_below_threshold": 0,
            "patterns_dead": 0,
            "step_count": 30
          },
          "memory_size": 1064
        }
      },
      {
        "top1": 0.06802721088435375,
        "topk": 0.3197278911564626,
        "cap_t_03": 0.2925170068027211,
        "cap_t_05": 0.0782312925170068,
        "recall_at_k": {
          "1": 0.06802721088435375,
          "5": 0.24489795918367346,
          "10": 0.3197278911564626,
          "20": 0.3435374149659864,
          "50": 0.3435374149659864
        },
        "per_scale": {
          "2": {
            "mean_top_score": 0.9998502021744138,
            "mean_entropy": 0.6845348079999288,
            "metastable_rate": 0.0,
            "recall_at_k": {
              "1": 0.04081632653061224,
              "5": 0.24489795918367346,
              "10": 0.3333333333333333,
              "20": 0.3877551020408163,
              "50": 0.46598639455782315
            },
            "mean_settled_synergy_at_mask": -0.023613277412111534,
            "atom_pair_geometry": {
              "n_pairs": 100000,
              "mean": 0.24001894973799587,
              "std": 0.02110469723197096,
              "p95": 0.26907471120357507,
              "p99": 0.2814843493700027,
              "max": 0.39571982622146606
            }
          },
          "3": {
            "mean_top_score": 0.9815549779505957,
            "mean_entropy": 0.6304039052960013,
            "metastable_rate": 0.24489795918367346,
            "recall_at_k": {
              "1": 0.05442176870748299,
              "5": 0.23469387755102042,
              "10": 0.3129251700680272,
              "20": 0.3843537414965986,
              "50": 0.4557823129251701
            },
            "mean_settled_synergy_at_mask": 0.05711514698887928,
            "atom_pair_geometry": {
              "n_pairs": 100000,
              "mean": 0.24001894973799587,
              "std": 0.02110469723197096,
              "p95": 0.26907471120357507,
              "p99": 0.2814843493700027,
              "max": 0.39571982622146606
            }
          },
          "4": {
            "mean_top_score": 0.9853066548603733,
            "mean_entropy": 0.5631860691268428,
            "metastable_rate": 0.11224489795918367,
            "recall_at_k": {
              "1": 0.09183673469387756,
              "5": 0.19727891156462585,
              "10": 0.24829931972789115,
              "20": 0.3231292517006803,
              "50": 0.3741496598639456
            },
            "mean_settled_synergy_at_mask": 0.029030148476064457,
            "atom_pair_geometry": {
              "n_pairs": 100000,
              "mean": 0.24001894973799587,
              "std": 0.02110469723197096,
              "p95": 0.26907471120357507,
              "p99": 0.2814843493700027,
              "max": 0.39571982622146606
            }
          }
        },
        "n": 294,
        "cues_seen": 2000,
        "condition": "phase4",
        "phase4_stats_w2": {
          "retrievals": 2000,
          "candidates_total": 31,
          "store": {
            "size": 0,
            "capacity": 500,
            "evicted": 0,
            "mean_gate": 0.0,
            "max_gate": 0.0,
            "mean_age": 0.0,
            "mean_tag_count": 0.0,
            "max_tag_count": 0,
            "mean_suppression": 0.0
          },
          "consolidation": {
            "n_patterns": 4127,
            "mean_strength": 0.02570969983935356,
            "max_strength": 16.966819763183594,
            "mean_u": [
              0.00987952295690775,
              0.01593882031738758,
              0.018286429345607758,
              0.017547816038131714,
              0.013757860288023949,
              0.007546090986579657
            ],
            "patterns_below_threshold": 0,
            "patterns_dead": 0,
            "step_count": 40
          },
          "memory_size": 4127
        },
        "phase4_stats_w3": {
          "retrievals": 2000,
          "candidates_total": 35,
          "store": {
            "size": 0,
            "capacity": 500,
            "evicted": 0,
            "mean_gate": 0.0,
            "max_gate": 0.0,
            "mean_age": 0.0,
            "mean_tag_count": 0.0,
            "max_tag_count": 0,
            "mean_suppression": 0.0
          },
          "consolidation": {
            "n_patterns": 2083,
            "mean_strength": 0.030895590782165527,
            "max_strength": 17.156414031982422,
            "mean_u": [
              0.012614692561328411,
              0.019061177968978882,
              0.02066098339855671,
              0.019242262467741966,
              0.01484046783298254,
              0.008072013035416603
            ],
            "patterns_below_threshold": 0,
            "patterns_dead": 0,
            "step_count": 40
          },
          "memory_size": 2083
        },
        "phase4_stats_w4": {
          "retrievals": 2000,
          "candidates_total": 40,
          "store": {
            "size": 0,
            "capacity": 500,
            "evicted": 0,
            "mean_gate": 0.0,
            "max_gate": 0.0,
            "mean_age": 0.0,
            "mean_tag_count": 0.0,
            "max_tag_count": 0,
            "mean_suppression": 0.0
          },
          "consolidation": {
            "n_patterns": 1064,
            "mean_strength": 0.04089772701263428,
            "max_strength": 20.801279067993164,
            "mean_u": [
              0.01789366453886032,
              0.025082161650061607,
              0.025234205648303032,
              0.022502988576889038,
              0.01692308858036995,
              0.009083706885576248
            ],
            "patterns_below_threshold": 0,
            "patterns_dead": 0,
            "step_count": 40
          },
          "memory_size": 1064
        }
      }
    ]
  }
}